event_web_scout/__init__.py
event_web_scout/plugin_interface.py
event_web_scout-0.0.1a24.dist-info/LICENSE
event_web_scout-0.0.1a24.dist-info/METADATA
event_web_scout-0.0.1a24.dist-info/WHEEL
event_web_scout-0.0.1a24.dist-info/top_level.txt
event_web_scout-0.0.1a24.dist-info/RECORD
