Metadata-Version: 2.1
Name: event-web-scout
Version: 0.0.1a24
Summary: Extendable package for collecting events from the web and adding them to Google calendars
Home-page: https://github.com/geeeezmo/event-web-scout
Author: Aleksandr Klimov
Author-email: 2767789+geeeezmo@users.noreply.github.com
Classifier: Development Status :: 2 - Pre-Alpha
Classifier: Intended Audience :: Other Audience
Classifier: Programming Language :: Python :: 3
Classifier: Operating System :: OS Independent
License-File: LICENSE
